teedoc_plugin_markdown_parser/__init__.py
teedoc_plugin_markdown_parser/plugin_details.py
teedoc_plugin_markdown_parser/plugin_subscript.py
teedoc_plugin_markdown_parser/plugin_superscript.py
teedoc_plugin_markdown_parser/plugin_tabset.py
teedoc_plugin_markdown_parser/renderer.py
teedoc_plugin_markdown_parser/renderer_base.py
teedoc_plugin_markdown_parser/renderer_math.py
teedoc_plugin_markdown_parser/renderer_new.py
teedoc_plugin_markdown_parser/renderer_old.py
teedoc_plugin_markdown_parser/assets/mermaid.min.js
teedoc_plugin_markdown_parser-2.11.0.dist-info/LICENSE
teedoc_plugin_markdown_parser-2.11.0.dist-info/METADATA
teedoc_plugin_markdown_parser-2.11.0.dist-info/WHEEL
teedoc_plugin_markdown_parser-2.11.0.dist-info/top_level.txt
teedoc_plugin_markdown_parser-2.11.0.dist-info/RECORD
